{"NUM_BUNDLE_FAIR_TRADE_LOANS": "uint16", "NUM_EASTERN_EUROPE_LOANS": "uint16", "ACCOUNT_AGE_MONTHS": "uint8", "NUM_OCEANIA_LOANS": "uint16", "FIRST_YEAR_DEPOSIT_OCCASION_NUM": "uint16", "NUM_SECTOR_CONSTRUCTION_LOANS": "uint16", "DIRECT_LOAN_PURCHASE_TOTAL": "float32", "LOGIN_ID": "uint32", "USER_LOCATION_STATE": "category", "FIRST_LOAN_COUNTRY": "category", "NUM_SECTOR_FOOD_LOANS": "uint32", "LAST_LOGIN_DATE": "category", "LIFETIME_LENDER_WEIGHTED_AVERAGE_LOAN_TERM": "float32", "NUM_AFRICA_LOANS": "uint32", "FIRST_TRANSACTION_DATE": "category", "NUM_BUNDLE_DISASTER_RECOVERY_LOANS": "uint16", "NUM_SECTOR_ENTERTAINMENT_LOANS": "uint16", "NUM_SECTOR_TRANSPORTATION_LOANS": "uint16", "PERCENT_FIRST_LOANS_EXPIRED": "float32", "LIFETIME_PROXY_LOAN_PURCHASE_TOTAL": "uint8", "NUM_SOUTH_AMERICA_LOANS": "uint32", "NUM_EXPIRING_SOON_LOANS": "uint16", "FIRST_LOAN_PURCHASE_WEIGHTED_AVERAGE_TERM": "float32", "FIRST_BASKET_CATEGORY": "category", "NUM_ASIA_LOANS": "uint32", "NUM_BUNDLE_YOUTH_LOANS": "uint16", "USER_LOCATION_COUNTRY": "category", "NUM_SECTOR_HOUSING_LOANS": "uint16", "NUM_BUNDLE_MOBILE_TECH_LOANS": "uint16", "NUM_BUNDLE_VULNERABLE_LOANS": "uint16", "CORE_LOAN_PURCHASE_NUM": "float32", "NUM_BUNDLE_HEALTH_LOANS": "uint16", "NUM_SECTOR_RETAIL_LOANS": "uint32", "LIFETIME_PROXY_LOAN_PURCHASE_NUM": "float32", "NUM_LOAN_COMMENTS": "uint16", "VINTAGE_MONTH": "uint32", "FIRST_YEAR_LOAN_PURCHASE_TOTAL": "uint32", "NUM_BUNDLE_RURAL_LOANS": "uint32", "NUM_BUNDLE_REFUGEE_LOANS": "uint16", "NUM_TEAM_LOANS": "uint32", "IS_FREE_TRIAL_USER": "category", "LIFETIME_DONATION_TOTAL": "float32", "LIFETIME_ACCOUNT_LOAN_PURCHASE_NUM": "float32", "NUM_NORTH_AMERICA_LOANS": "uint16", "DIRECT_LOAN_PURCHASE_NUM": "float32", "FIRST_TIME_DEPOSITOR_REPORTING_CATEGORY": "category", "NUM_BUNDLE_UNDERFUNDED_LOANS": "uint16", "NUM_SECTOR_SERVICE_LOANS": "uint16", "NUM_BUNDLE_SOCIAL_ENTERPRISE_LOANS": "uint16", "NUM_TEAM_MEMBERSHIPS": "uint16", "LIFETIME_DONATION_NUM": "float32", "NUM_SECTOR_HEALTH_LOANS": "uint16", "NUMBER_OF_FIRST_LOANS_STILL_OUTSTANDING": "float32", "NUM_BUNDLE_STARTUP_LOANS": "uint16", "NUM_BUNDLE_HIGHER_ED_LOANS": "uint16", "FIRST_YEAR_EMAIL_REFERRAL_LOAN_PURCHASE_OCCASION_NUM": "uint16", "PERCENT_FIRST_LOANS_DEFAULTED": "float32", "NUM_BUNDLE_CONFLICT_ZONE_LOANS": "uint16", "IS_INACTIVE_CREDIT_DONOR": "bool", "NUM_CENTRAL_AMERICA_LOANS": "uint16", "FIRST_YEAR_LOAN_PURCHASE_OCCASION_NUM": "uint16", "NUM_BUNDLE_GREEN_LOANS": "uint16", "LIFETIME_DEPOSIT_TOTAL": "float32", "LAST_TRANSACTION_DATE": "category", "NUM_DISTINCT_COUNTRIES_LENT_TO": "uint8", "FUND_ACCOUNT_ID": "uint32", "NUM_BUNDLE_SOLAR_LOANS": "uint16", "NUM_BUNDLE_CLEAN_ENERGY_LOANS": "uint16", "NUM_STATEMENT_COMMENTS": "uint16", "FIRST_YEAR_DEPOSIT_TOTAL": "float32", "NUM_SECTOR_CLOTHING_LOANS": "uint16", "FIRST_TRANSACTION_REFERRAL": "category", "NUM_BUNDLE_GROWING_BUSINESSES_LOANS": "uint16", "NUM_SECTOR_WHOLESALE_LOANS": "uint16", "PERCENT_FIRST_LOANS_REPAID": "float32", "NUM_SECTOR_EDUCATION_LOANS": "uint16", "LIFETIME_DEPOSIT_NUM": "float32", "NUMBER_OF_LOANS_IN_FIRST_LOAN_CHECKOUT": "float32", "FIRST_DAY_LOAN_PURCHASE_TOTAL": "uint16", "FIRST_YEAR_DONATION_OCCASION_NUM": "uint16", "NUM_BUNDLE_WATER_LOANS": "uint16", "FIRST_DAY_DEPOSIT_TOTAL": "float32", "FIRST_YEAR_EMAIL_REFERRAL_DONATION_TOTAL": "int64", "FIRST_DEPOSIT_DATE": "category", "NUM_BUNDLE_INNOVATIVE_LOANS": "uint16", "USER_LOCATION_CITY": "category", "ACTIVE_LIFETIME_MONTHS": "float32", "FIRST_YEAR_DONATION_TOTAL": "float32", "NUM_SECTOR_PERSONAL_USE_LOANS": "uint16", "VINTAGE_DATE": "category", "FIRST_LOAN_REGION": "category", "VINTAGE_YEAR": "uint16", "CORE_LOAN_PURCHASE_TOTAL": "float32", "LIFETIME_ACCOUNT_LOAN_PURCHASE_TOTAL": "uint32", "NUM_SECTOR_AGRICULTURE_LOANS": "uint32", "NUM_TEAM_MESSAGES": "uint16", "FIRST_DAY_DONATION_TOTAL": "float32", "FIRST_YEAR_EMAIL_REFERRAL_LOAN_PURCHASE_TOTAL": "int64", "NUM_SECTOR_MANUFACTURING_LOANS": "uint16", "NUM_SECTOR_ARTS_LOANS": "uint16", "NUM_JOURNAL_COMMENTS": "uint16", "IS_CORPORATE_CAMPAIGN_USER": "category", "NUM_BUNDLE_ISLAMIC_FINANCE_LOANS": "uint16", "FIRST_YEAR_EMAIL_REFERRAL_DONATION_OCCASION_NUM": "uint8", "NUM_BUNDLE_JOB_CREATION_SME_LOANS": "uint16"}